hashinator/__init__.py
hashinator/hashes.py
hashinator/utils.py
hashinator-0.1.22.dist-info/LICENSE
hashinator-0.1.22.dist-info/METADATA
hashinator-0.1.22.dist-info/WHEEL
hashinator-0.1.22.dist-info/top_level.txt
hashinator-0.1.22.dist-info/RECORD
